jque/__init__.py
jque-0.1.3.dist-info/METADATA
jque-0.1.3.dist-info/RECORD
jque-0.1.3.dist-info/WHEEL
jque-0.1.3.dist-info/top_level.txt
