Metadata-Version: 2.1
Name: jque
Version: 0.1.3
Summary: Query JSON in memory as though it were a Mongo database.
Home-page: https://github.com/j6k4m8/jque
Author: Jordan Matelsky
Author-email: opensource@matelsky.com
License: MIT
Platform: UNKNOWN
Classifier: License :: OSI Approved :: MIT License
Classifier: Programming Language :: Python
Classifier: Programming Language :: Python :: 3
Classifier: Programming Language :: Python :: 3.6
Requires-Python: >=3.6.0
Provides-Extra: dev
Requires-Dist: deco
Provides-Extra: dev
Requires-Dist: pytest; extra == 'dev'
Requires-Dist: pylint; extra == 'dev'
